{
	"id" : "title",
	"type" : "Node",
	"params" :
	{
		"background_color" : "<255, 255, 255",
		"pos_x" : 0.5,
		"pos_y" : 0.5,
		"anch_x" : 0.5,
		"anch_y" : 0.5,
		"content_size" : "!3840, 2160",
		"layer" : 1,
		"opacity" : 0
	},
	"children" : 
	{
		"title_logo" : 
		{
			"type" : "Sprite",
			"id" : "logo_sprite",
			"params" :
			{
				"sprite_frame": "Title.png",
				"pos_x" : 0.5,
				"pos_y" : 0.7,
				"anch_x" : 0.5,
				"anch_y" : 0.5,
				"layer" : 1,
				"opacity" : 0
			}
		}
	},
	"on_enter_cutscene": "configs/cutscenes/intro.json"
}